cw_download_chess_com_games/__init__.py
cw_download_chess_com_games/cw_download_chess_com_games.py
cw_download_chess_com_games-1.0.0.dist-info/LICENSE.txt
cw_download_chess_com_games-1.0.0.dist-info/METADATA
cw_download_chess_com_games-1.0.0.dist-info/WHEEL
cw_download_chess_com_games-1.0.0.dist-info/entry_points.txt
cw_download_chess_com_games-1.0.0.dist-info/top_level.txt
cw_download_chess_com_games-1.0.0.dist-info/RECORD
