Metadata-Version: 2.1
Name: cw-download-chess-com-games
Version: 1.0.0
Summary: Download all chess.com games.
Home-page: https://github.com/ChameleonRed/cw_download_chess_com_games
Author: Cezary K. Wagner
Author-email: Cezary.Wagner@gmail.com
License: http://creativecommons.org/licenses/by-nc-nd/4.0
Platform: UNKNOWN
Classifier: Development Status :: 5 - Production/Stable
Classifier: Environment :: Console
Classifier: Environment :: Win32 (MS Windows)
Classifier: Intended Audience :: End Users/Desktop
Classifier: License :: Free for non-commercial use
Classifier: Operating System :: MacOS
Classifier: Operating System :: Microsoft :: Windows
Classifier: Operating System :: OS Independent
Classifier: Programming Language :: Python :: 3
Classifier: Programming Language :: Python :: 3.10
Classifier: Topic :: Games/Entertainment
Classifier: Topic :: Games/Entertainment :: Board Games
Classifier: Topic :: Education
Requires-Python: >=3.10
License-File: LICENSE.txt
